postr/__init__.py
postr/client.py
postr/model/__init__.py
postr/model/event.py
postr/model/filter.py
postr/model/messages.py
postr/relay/__init__.py
postr/relay/connection.py
postr/relay/retry.py
postr/user.py
postr-0.1.0.dist-info/METADATA
postr-0.1.0.dist-info/WHEEL
postr-0.1.0.dist-info/RECORD
