Metadata-Version: 2.1
Name: postr
Version: 0.1.0
Summary: Small python nostr client
Author: Your Name
Author-email: you@example.com
Requires-Python: >=3.10,<4.0
Classifier: Programming Language :: Python :: 3
Classifier: Programming Language :: Python :: 3.10
Classifier: Programming Language :: Python :: 3.11
Requires-Dist: coincurve (>=18.0.0,<19.0.0)
Requires-Dist: pydantic (>=1.10.4,<2.0.0)
Requires-Dist: rel (>=0.4.7,<0.5.0)
Requires-Dist: socketify (>=0.0.5,<0.0.6)
Requires-Dist: websocket-client (>=1.4.2,<2.0.0)
Requires-Dist: websockets (>=10.4,<11.0)
